pypi_packaging_tutorial/__init__.py
pypi_packaging_tutorial/data/datafile.py
pypi_packaging_tutorial/divide/__init__.py
pypi_packaging_tutorial/divide/divide_by_three.py
pypi_packaging_tutorial/example.py
pypi_packaging_tutorial/multiply/__init__.py
pypi_packaging_tutorial/multiply/multiply_by_three.py
pypi_packaging_tutorial-0.1.5.13.dist-info/LICENSE.txt
pypi_packaging_tutorial-0.1.5.13.dist-info/METADATA
pypi_packaging_tutorial-0.1.5.13.dist-info/WHEEL
pypi_packaging_tutorial-0.1.5.13.dist-info/RECORD
